txts/__init__.py
txts/api.py
txts.py-1.0.dist-info/LICENSE.md
txts.py-1.0.dist-info/METADATA
txts.py-1.0.dist-info/WHEEL
txts.py-1.0.dist-info/top_level.txt
txts.py-1.0.dist-info/RECORD
