Metadata-Version: 2.1
Name: txts.py
Version: 1.0
Summary: Python wrapper for interacting with txts
Home-page: https://github.com/txts-team/txts.py/
Author: smugay
License: MIT
Classifier: Programming Language :: Python :: 3 :: Only
Classifier: License :: OSI Approved :: MIT License
Requires-Python: >=3.3
License-File: LICENSE.md
Requires-Dist: beautifulsoup4 ==4.12.2
Requires-Dist: Requests ==2.31.0
